README.rst
setup.py
easyos/__init__.py
easyos/easyos.py
easyos.egg-info/PKG-INFO
easyos.egg-info/SOURCES.txt
easyos.egg-info/dependency_links.txt
easyos.egg-info/top_level.txt