Metadata-Version: 1.1
Name: easyos
Version: 2.2
Summary: Common OS attributes in a user-friendly format.
Home-page: http://github.com/tristanfisher/easyos
Author: Tristan Fisher
Author-email: code@tristanfisher.com
License: Apache 2.0
Keywords: os environment operating system
Platform: UNKNOWN
Classifier: Environment :: MacOS X
Classifier: Environment :: Win32 (MS Windows)
Classifier: Intended Audience :: Developers
Classifier: License :: OSI Approved :: Apache Software License
Classifier: Operating System :: MacOS
Classifier: Operating System :: Microsoft
Classifier: Operating System :: Unix
Classifier: Programming Language :: Python
Classifier: Programming Language :: Python :: 3
Classifier: Programming Language :: Python :: 3 :: Only
Classifier: Programming Language :: Python :: 3.4
Classifier: Topic :: Utilities
